causal_profiler/__init__.py
causal_profiler/causal_profiler.py
causal_profiler/constants.py
causal_profiler/kernels.py
causal_profiler/mechanism.py
causal_profiler/query.py
causal_profiler/query_estimator.py
causal_profiler/sampler.py
causal_profiler/scm.py
causal_profiler/space_of_interest.py
causal_profiler/utils.py
causal_profiler/variable.py
causal_profiler-0.1.1.dist-info/licenses/LICENSE
causal_profiler-0.1.1.dist-info/METADATA
causal_profiler-0.1.1.dist-info/WHEEL
causal_profiler-0.1.1.dist-info/top_level.txt
causal_profiler-0.1.1.dist-info/RECORD
