Metadata-Version: 2.4
Name: causal-profiler
Version: 0.1.1
Summary: A Synthetic Benchmark Generator for Causal Machine Learning
Author-email: panispani <p.panayiotou2@gmail.com>
License-Expression: MIT
Requires-Python: >=3.10
License-File: LICENSE
Requires-Dist: numpy
Requires-Dist: torch
Requires-Dist: pyyaml
Provides-Extra: dev
Requires-Dist: pytest; extra == "dev"
Requires-Dist: tox; extra == "dev"
Requires-Dist: pandas; extra == "dev"
Requires-Dist: scipy; extra == "dev"
Requires-Dist: statsmodels; extra == "dev"
Requires-Dist: networkx; extra == "dev"
Provides-Extra: examples
Requires-Dist: pyyaml; extra == "examples"
Requires-Dist: pandas; extra == "examples"
Requires-Dist: matplotlib; extra == "examples"
Requires-Dist: seaborn; extra == "examples"
Dynamic: license-file
